eo_lib/__init__.py
eo_lib/application/__init__.py
eo_lib/application/abstract_application.py
eo_lib/application/factories.py
eo_lib/application/core/__init__.py
eo_lib/application/core/application.py
eo_lib/application/relationship/__init__.py
eo_lib/application/relationship/application.py
eo_lib/application/team/__init__.py
eo_lib/application/team/application.py
eo_lib/config/__init__.py
eo_lib/config/base.py
eo_lib/config/config.py
eo_lib/model/__init__.py
eo_lib/model/factories.py
eo_lib/model/core/__init__.py
eo_lib/model/core/models.py
eo_lib/model/relationship/__init__.py
eo_lib/model/relationship/models.py
eo_lib/model/team/__init__.py
eo_lib/model/team/models.py
eo_lib/service/__init__.py
eo_lib/service/base_service.py
eo_lib/service/factories.py
eo_lib/service/core/__init__.py
eo_lib/service/core/service.py
eo_lib/service/relationship/__init__.py
eo_lib/service/relationship/service.py
eo_lib/service/team/__init__.py
eo_lib/service/team/service.py
eo_lib-1.0.24.dist-info/METADATA
eo_lib-1.0.24.dist-info/WHEEL
eo_lib-1.0.24.dist-info/top_level.txt
eo_lib-1.0.24.dist-info/RECORD
