Metadata-Version: 2.1
Name: eo-lib
Version: 1.0.24
Summary: The Enterprise Ontology (EO) aims at establishing a common conceptualization on the Entreprise domain, including organizations, organizational units, people, roles, teams and projects. Currently, it as considered external to SEON
Home-page: https://gitlab.com/ontologyasaservice/data/core/enterprise-ontology-service
Author: paulossjunior
Author-email: paulossjunior@gmail.com
License: UNKNOWN
Platform: UNKNOWN
Classifier: Programming Language :: Python :: 3
Classifier: License :: OSI Approved :: MIT License
Classifier: Operating System :: OS Independent
Requires-Dist: SQLAlchemy
Requires-Dist: SQLAlchemy-Utils
Requires-Dist: psycopg2-binary
Requires-Dist: factory-boy
Requires-Dist: SQLAlchemy-serializer
